llama_index/embeddings/huggingface/__init__.py
llama_index/embeddings/huggingface/base.py
llama_index/embeddings/huggingface/pooling.py
llama_index/embeddings/huggingface/utils.py
llama_index_embeddings_huggingface-0.5.5.dist-info/METADATA
llama_index_embeddings_huggingface-0.5.5.dist-info/WHEEL
llama_index_embeddings_huggingface-0.5.5.dist-info/RECORD
