Metadata-Version: 2.4
Name: llama-index-embeddings-huggingface
Version: 0.5.5
Summary: llama-index embeddings huggingface integration
Author-email: Your Name <you@example.com>
License-Expression: MIT
Requires-Python: <4.0,>=3.9
Requires-Dist: huggingface-hub[inference]>=0.19.0
Requires-Dist: llama-index-core<0.13,>=0.12.0
Requires-Dist: sentence-transformers>=2.6.1
